simple_commands/__init__.py
simple_commands/help.py
simple_commands/math_.py
simple_commands/password.py
simple_commands/CLASS/ProgressBar/__init__.py
simple_commands/CLASS/ProgressBar/error.py
simple_commands/CLASS/ProgressBar/progressBar.py
simple_commands/CLASS/ProgressBar/test.py
simple_commands/CLASS/SQL_class/SQL.py
simple_commands/CLASS/time_zone/time_zone.py
simple_commands/file/decorator.py
simple_commands/file/file.py
simple_commands/file/savedata.py
simple_commands/file/deletedata/deleted_files.db
simple_commands/file/savedata/__main__.txt
simple_commands/img/image.py
simple_commands-1.4.5.dist-info/LICENSE
simple_commands-1.4.5.dist-info/METADATA
simple_commands-1.4.5.dist-info/WHEEL
simple_commands-1.4.5.dist-info/top_level.txt
simple_commands-1.4.5.dist-info/RECORD
