Metadata-Version: 2.1
Name: simple-commands
Version: 1.4.5
Summary: It is a library designed to be easy to use. We understand how difficult some things can be, so we strive to make it as user-friendly as possible.
Classifier: Development Status :: 3 - Alpha
Classifier: Intended Audience :: Developers
Classifier: License :: OSI Approved :: MIT License
Classifier: Programming Language :: Python :: 3
Classifier: Programming Language :: Python :: 3.9
Classifier: Programming Language :: Python :: 3.10
Classifier: Programming Language :: Python :: 3.11
Requires-Python: >=3.9
License-File: LICENSE
Requires-Dist: pillow
Requires-Dist: numpy
Requires-Dist: opencv-python
Requires-Dist: tqdm
Requires-Dist: pytz
Requires-Dist: imagehash
